.DS_Store
gym_jiminy/toolbox/__init__.py
gym_jiminy/toolbox/py.typed
gym_jiminy/toolbox/compositions/__init__.py
gym_jiminy/toolbox/compositions/locomotion.py
gym_jiminy/toolbox/math/__init__.py
gym_jiminy/toolbox/math/qhull.py
gym_jiminy/toolbox/math/spline.py
gym_jiminy/toolbox/quantities/__init__.py
gym_jiminy/toolbox/quantities/locomotion.py
gym_jiminy/toolbox/wrappers/__init__.py
gym_jiminy/toolbox/wrappers/frame_rate_limiter.py
gym_jiminy/toolbox/wrappers/meta_envs.py
gym_jiminy_toolbox-1.8.13.dist-info/METADATA
gym_jiminy_toolbox-1.8.13.dist-info/WHEEL
gym_jiminy_toolbox-1.8.13.dist-info/top_level.txt
gym_jiminy_toolbox-1.8.13.dist-info/RECORD
