Metadata-Version: 2.2
Name: gym-jiminy-toolbox
Version: 1.8.13
Summary: Generic Reinforcement learning toolbox based on Pytorch for Gym Jiminy.
Author: Alexis Duburcq
Author-email: alexis.duburcq@gmail.com
Maintainer: Alexis Duburcq
License: MIT
Keywords: reinforcement-learning robotics gym jiminy
Classifier: Development Status :: 3 - Alpha
Classifier: Intended Audience :: Science/Research
Classifier: Topic :: Scientific/Engineering :: Artificial Intelligence
Classifier: Topic :: Software Development :: Libraries :: Python Modules
Classifier: License :: OSI Approved :: MIT License
Classifier: Programming Language :: Python :: 3.10
Classifier: Programming Language :: Python :: 3.11
Classifier: Programming Language :: Python :: 3.12
Classifier: Programming Language :: Python :: 3.13
Requires-Python: >=3.10,<3.14
Requires-Dist: gym-jiminy~=1.8.13
Requires-Dist: scipy
Dynamic: author
Dynamic: author-email
Dynamic: classifier
Dynamic: keywords
Dynamic: license
Dynamic: maintainer
Dynamic: requires-dist
Dynamic: requires-python
Dynamic: summary
